<?xml version="1.0" encoding="UTF-8"?>
<!DOCTYPE hibernate-mapping PUBLIC "-//Hibernate/Hibernate Mapping DTD 3.0//EN" "http://hibernate.sourceforge.net/hibernate-mapping-3.0.dtd">
<hibernate-mapping package="com.floreantpos.model">
	<class lazy="false" name="com.floreantpos.model.ShopTable" table="SHOP_TABLE">
		<id column="ID" name="id" type="java.lang.Integer">
			<generator class="assigned" />
		</id>

		<property column="NAME" name="name" type="java.lang.String"	length="20" />
		<property column="DESCRIPTION" name="description" type="java.lang.String" length="60" />
		<property column="CAPACITY" name="capacity" type="java.lang.Integer" />
		<property column="X" name="x" type="java.lang.Integer" />
		<property column="Y" name="y" type="java.lang.Integer" />

		<property column="FREE" name="free" type="java.lang.Boolean" />
		<property column="SERVING" name="serving" type="java.lang.Boolean" />
		<property column="BOOKED" name="booked" type="java.lang.Boolean" />
		<property column="DIRTY" name="dirty" type="java.lang.Boolean" />
		<property column="DISABLE" name="disable" type="java.lang.Boolean" />

		<!-- Associations -->

		<bag cascade="none" inverse="false" lazy="false" name="types" table="TABLE_TYPE_RELATION">
			<key column="TABLE_ID" />
			<many-to-many column="TYPE_ID" class="com.floreantpos.model.ShopTableType" />
		</bag>

		<many-to-one class="ShopFloor" name="floor" column="FLOOR_ID" />
	</class>
</hibernate-mapping>
